status_whimsy/__init__.py
status_whimsy/core.py
status_whimsy-0.2.0.dist-info/licenses/LICENSE
status_whimsy-0.2.0.dist-info/METADATA
status_whimsy-0.2.0.dist-info/WHEEL
status_whimsy-0.2.0.dist-info/top_level.txt
status_whimsy-0.2.0.dist-info/RECORD
