Metadata-Version: 2.4
Name: status-whimsy
Version: 0.2.0
Summary: A lightweight library for generating whimsical status updates using Claude Haiku 4
Author: Richard Atkinson
License: MIT
Project-URL: Homepage, https://github.com/RichardAtCT/status-whimsy
Project-URL: Documentation, https://github.com/RichardAtCT/status-whimsy#readme
Project-URL: Repository, https://github.com/RichardAtCT/status-whimsy
Project-URL: Issues, https://github.com/RichardAtCT/status-whimsy/issues
Keywords: status,whimsy,claude,anthropic,ai,creative-writing
Classifier: Development Status :: 4 - Beta
Classifier: Intended Audience :: Developers
Classifier: License :: OSI Approved :: MIT License
Classifier: Programming Language :: Python :: 3
Classifier: Programming Language :: Python :: 3.9
Classifier: Programming Language :: Python :: 3.10
Classifier: Programming Language :: Python :: 3.11
Classifier: Programming Language :: Python :: 3.12
Classifier: Topic :: Software Development :: Libraries :: Python Modules
Classifier: Topic :: Text Processing :: General
Classifier: Topic :: Utilities
Requires-Python: >=3.9
License-File: LICENSE
Requires-Dist: anthropic>=0.18.0
Provides-Extra: dev
Requires-Dist: pytest>=7.0; extra == "dev"
Requires-Dist: pytest-cov; extra == "dev"
Requires-Dist: black; extra == "dev"
Requires-Dist: isort; extra == "dev"
Requires-Dist: flake8; extra == "dev"
Requires-Dist: mypy; extra == "dev"
Dynamic: license-file
